{
  "setting": {},
  "condition": {
    "plugin": {
      "list": []
    },
    "game": {
      "list": []
    },
    "gamePlugin": {
      "list": []
    },
    "miniprogram": {
      "list": [
        {
          "name": "个人中心",
          "pathName": "pages/my/my",
          "query": "",
          "launchMode": "default",
          "scene": null
        },
        {
          "name": "就诊人管理",
          "pathName": "pages/myPatient/myPatient",
          "query": "",
          "launchMode": "default",
          "scene": null
        },
        {
          "name": "就诊人列表",
          "pathName": "pages/myPatient/myPatient",
          "query": "",
          "launchMode": "default",
          "scene": null
        },
        {
          "name": "我的订单",
          "pathName": "pages/myOrder/myOrder",
          "query": "",
          "launchMode": "default",
          "scene": null
        },
        {
          "name": "防疫论坛",
          "pathName": "pages/luntan/luntan",
          "query": "",
          "launchMode": "default",
          "scene": null
        },
        {
          "name": "订单详情",
          "pathName": "pages/orderDetail/orderDetail",
          "query": "id=efbc6d716243c56802d14ca311dea31c",
          "scene": null,
          "launchMode": "default"
        },
        {
          "name": "核酸检测预约",
          "pathName": "pages/hesuanjiance/hesuanjiance",
          "query": "",
          "launchMode": "default",
          "scene": null
        },
        {
          "name": "核酸结果查询",
          "pathName": "pages/hesuanjieguo/hesuanjieguo",
          "query": "detail=true",
          "launchMode": "default",
          "scene": null
        },
        {
          "name": "疫苗查询",
          "pathName": "pages/yimiaochaxun/yimiaochaxun",
          "query": "",
          "launchMode": "default",
          "scene": null
        },
        {
          "name": "疫苗预约",
          "pathName": "pages/yimiaoyuyue/yimiaoyuyue",
          "query": "",
          "launchMode": "default",
          "scene": null
        },
        {
          "name": "机构查询",
          "pathName": "pages/group/group",
          "query": "",
          "launchMode": "default",
          "scene": null
        },
        {
          "name": "老幼查询",
          "pathName": "pages/laoyouchaxun/laoyouchaxun",
          "query": "",
          "launchMode": "default",
          "scene": null
        },
        {
          "name": "高风险地区",
          "pathName": "pages/fengxian/fengxian",
          "query": "",
          "launchMode": "default",
          "scene": null
        },
        {
          "name": "套餐详情",
          "pathName": "pages/yimiaoDetail/yimiaoDetail",
          "query": "",
          "launchMode": "default",
          "scene": null
        },
        {
          "name": "论坛",
          "pathName": "pages/luntan/luntan",
          "query": "",
          "launchMode": "default",
          "scene": null
        },
        {
          "name": "我的收藏",
          "pathName": "pages/myCollect/myCollect",
          "query": "",
          "launchMode": "default",
          "scene": null
        },
        {
          "name": "疫苗剂次",
          "pathName": "pages/yimiaoSubmit/yimiaoSubmit",
          "query": "id=d2fe6f2062397eb40120f1251886f38e",
          "launchMode": "default",
          "scene": null
        },
        {
          "name": "疫情科普",
          "pathName": "pages/yiqingkepu/yiqingkepu",
          "query": "",
          "launchMode": "default",
          "scene": null
        },
        {
          "name": "团体预约",
          "pathName": "pages/tuanti/tuanti",
          "query": "",
          "launchMode": "default",
          "scene": null
        },
        {
          "name": "反馈界面 ",
          "pathName": "pages/feedback/feedback",
          "query": "",
          "launchMode": "default",
          "scene": null
        },
        {
          "name": "添加就诊人",
          "pathName": "pages/addPatient/addPatient",
          "query": "",
          "launchMode": "default",
          "scene": null
        },
        {
          "name": "detail",
          "pathName": "pages/newDetail/newDetail",
          "query": "",
          "launchMode": "default",
          "scene": null
        },
        {
          "name": "点赞页面",
          "pathName": "pages/myDianzan/myDianzan",
          "query": "",
          "launchMode": "default",
          "scene": null
        },
        {
          "name": "我的收藏-debug",
          "pathName": "pages/myCollect/myCollect",
          "query": "",
          "launchMode": "default",
          "scene": null
        },
        {
          "name": "我的评论",
          "pathName": "pages/myComment/myComment",
          "query": "",
          "launchMode": "default",
          "scene": null
        },
        {
          "name": "我的收藏",
          "pathName": "pages/myCollect/myCollect",
          "query": "",
          "launchMode": "default",
          "scene": null
        },
        {
          "name": "团体预约",
          "pathName": "pages/tuanti/tuanti",
          "query": "",
          "launchMode": "default",
          "scene": null
        },
        {
          "name": "",
          "pathName": "pages/yimiaoDetail/yimiaoDetail",
          "query": "id=d2fe6f20623f1db50248f7e533b3e2fd",
          "launchMode": "default",
          "scene": null
        },
        {
          "name": "精简核酸结果",
          "pathName": "pages/hesuanjieguo/hesuanjieguo",
          "query": "",
          "launchMode": "default",
          "scene": null
        },
        {
          "name": "老幼助查detail",
          "pathName": "pages/hesuanjieguo/hesuanjieguo",
          "query": "id=6360507662425a29023c0b8536b4b516",
          "launchMode": "default",
          "scene": null
        },
        {
          "name": "",
          "pathName": "pages/hesuanjieguo/hesuanjieguo",
          "query": "",
          "launchMode": "default",
          "scene": null
        },
        {
          "name": "检测报告进度",
          "pathName": "pages/myReportProcess/myReportProcess",
          "query": "",
          "launchMode": "default",
          "scene": null
        },
        {
          "name": "界面结果查询",
          "pathName": "pages/hesuanjieguo/hesuanjieguo",
          "query": "",
          "launchMode": "default",
          "scene": null
        }
      ]
    }
  }
}